{
	"view" : {
		"anchor-x" : "left",
		"anchor-y" : "bottom",
		"class" : "view",
		"height" : 78,
		"inherit-position" : true,
		"name" : "rootView",
		"position-x" : "left",
		"position-y" : "bottom",
		"width" : 110,
		"children" : [
			{
				"anchor-x" : "center",
				"anchor-y" : "center",
				"class" : "view",
				"height" : 64,
				"margin-bottom" : 7,
				"margin-left" : 0,
				"margin-right" : 0,
				"margin-top" : 0,
				"name" : "defensiveView",
				"position-x" : "center",
				"position-y" : "center",
				"scale" : 0.7,
				"width" : 64,
				"children" : [
					{
						"anchor-x" : "center",
						"anchor-y" : "center",
						"cell-json" : "hp_combat_interaction_choices_cell.json",
						"class" : "image",
						"height" : 64,
						"image" : "hp_container_stance_blue.png",
						"margin-bottom" : 0,
						"margin-left" : 0,
						"margin-right" : 0,
						"margin-top" : 0,
						"name" : "defensiveStanceBg",
						"position-x" : "center",
						"position-y" : "center",
						"sizing" : "SpriteFill",
						"width" : 64
					},
					{
						"anchor-x" : "center",
						"anchor-y" : "center",
						"cell-json" : "hp_combat_interaction_choices_cell.json",
						"class" : "image",
						"dynamic-img" : true,
						"height" : 64,
						"image" : "hp_icon_rps_sneaky.png",
						"margin-bottom" : 0,
						"margin-left" : 0,
						"margin-right" : 0,
						"margin-top" : 0,
						"name" : "defensiveStanceIcon",
						"position-x" : "center",
						"position-y" : "center",
						"sizing" : "SpriteFill",
						"width" : 64
					}
				]
			},
			{
				"actions" : [],
				"anchor-x" : "center",
				"anchor-y" : "center",
				"class" : "button",
				"height" : 78,
				"image" : "invisible.png",
				"margin-bottom" : 0,
				"margin-left" : 0,
				"margin-right" : 0,
				"margin-top" : 0,
				"name" : "stanceButton",
				"position-x" : "center",
				"position-y" : "center",
				"width" : 110,
				"children" : [
					{
						"anchor-x" : "center",
						"anchor-y" : "center",
						"class" : "view",
						"height" : 64,
						"margin-bottom" : 7,
						"margin-left" : 0,
						"margin-right" : 0,
						"margin-top" : 0,
						"name" : "stanceColorView",
						"position-x" : "center",
						"position-y" : "center",
						"width" : 64,
						"children" : [
							{
								"anchor-x" : "center",
								"anchor-y" : "center",
								"class" : "image",
								"height" : 64,
								"image" : "hp_container_stance_blue.png",
								"margin-bottom" : 0,
								"margin-left" : 0,
								"margin-right" : 0,
								"margin-top" : 0,
								"name" : "stanceIconBg",
								"position-x" : "center",
								"position-y" : "center",
								"width" : 64
							},
							{
								"anchor-x" : "center",
								"anchor-y" : "center",
								"cell-json" : "hp_combat_interaction_choices_cell.json",
								"class" : "image",
								"dynamic-img" : true,
								"height" : 64,
								"image" : "hp_icon_combat_sneaky.png",
								"margin-bottom" : 0,
								"margin-left" : 0,
								"margin-right" : 0,
								"margin-top" : 0,
								"name" : "stanceIcon",
								"position-x" : "center",
								"position-y" : "center",
								"sizing" : "SpriteFill",
								"width" : 64
							}
						]
					},
					{
						"anchor-x" : "center",
						"anchor-y" : "center",
						"class" : "view",
						"editor-layerExpanded" : false,
						"margin-bottom" : 0,
						"margin-left" : 0,
						"margin-right" : 0,
						"margin-top" : 0,
						"name" : "stanceLabelView",
						"percent-height" : 1,
						"percent-width" : 1,
						"position-x" : "center",
						"position-y" : "center",
						"children" : [
							{
								"9slicescalezone-height" : 0.333,
								"9slicescalezone-width" : 0.333,
								"9slicescalezone-x" : 0.333,
								"9slicescalezone-y" : 0.333,
								"anchor-x" : "left",
								"anchor-y" : "bottom",
								"class" : "image",
								"editor-layerExpanded" : false,
								"height" : 26,
								"image" : "hp_container_text_gold.png",
								"margin-bottom" : 0.5,
								"margin-left" : 1,
								"margin-right" : 0,
								"margin-top" : 0,
								"name" : "text_gold",
								"position-x" : "left",
								"position-y" : "bottom",
								"width" : 108,
								"children" : [
									{
										"alignment" : "center",
										"anchor-x" : "center",
										"anchor-y" : "center",
										"cell-json" : "hp_combat_interaction_choices_cell.json",
										"class" : "label",
										"color" : [
											255,
											255,
											255
										],
										"dynamic-text" : true,
										"font" : "Avenir-Book",
										"font-size" : 14,
										"image" : "hp_icon_combat_defensive.png",
										"margin-bottom" : 0,
										"margin-left" : 0,
										"margin-right" : 0,
										"margin-top" : 0,
										"name" : "stanceLabel",
										"position-x" : "center",
										"position-y" : "center",
										"sizing" : "SpriteFill",
										"text" : "Sneaky",
										"width" : 100
									}
								]
							},
							{
								"9slicescalezone-height" : 0.333,
								"9slicescalezone-width" : 0.333,
								"9slicescalezone-x" : 0.333,
								"9slicescalezone-y" : 0.333,
								"anchor-x" : "center",
								"anchor-y" : "top",
								"class" : "image",
								"height" : 3,
								"image" : "hp_container_stance_black.png",
								"margin-bottom" : 26,
								"margin-left" : 0,
								"margin-right" : 0,
								"margin-top" : 0,
								"name" : "stance_rectangle_bg",
								"position-x" : "center",
								"position-y" : "bottom",
								"width" : 32
							}
						]
					}
				]
			}
		]
	},
	"version" : "1.8.8.3"
}